axado_calculator/__init__.py
axado_calculator/axado.py
axado_calculator/config.py
axado_calculator/exceptions.py
axado_calculator/models.py
axado_calculator/tests.py
axado_calculator/utils.py
axado_calculator/assets/tabela/preco_por_kg.csv
axado_calculator/assets/tabela/rotas.csv
axado_calculator/assets/tabela2/preco_por_kg.tsv
axado_calculator/assets/tabela2/rotas.tsv
axado_calculator/logs/.keep
axado_challenge-1.2.3.dist-info/DESCRIPTION.rst
axado_challenge-1.2.3.dist-info/METADATA
axado_challenge-1.2.3.dist-info/RECORD
axado_challenge-1.2.3.dist-info/WHEEL
axado_challenge-1.2.3.dist-info/entry_points.txt
axado_challenge-1.2.3.dist-info/metadata.json
axado_challenge-1.2.3.dist-info/top_level.txt
