Metadata-Version: 2.0
Name: axado-challenge
Version: 1.2.3
Summary: This is a challenge job for Axado company
Home-page: https://github.com/AlexandreProenca/axado-challenge
Author: Alexandre Proença
Author-email: alexandre.proenca@hotmail.com.br
License: MIT
Keywords: Shell Calculator
Platform: UNKNOWN
Classifier: Development Status :: 2 - Pre-Alpha
Classifier: Intended Audience :: Developers
Classifier: License :: OSI Approved :: MIT License
Classifier: Operating System :: OS Independent
Classifier: Programming Language :: Python
Classifier: Programming Language :: Python :: 3
